SetCalcPy/Set.py
SetCalcPy/__init__.py
SetCalcPy/powerSet/__init__.py
SetCalcPy/powerSet/powerSetCalc.py
SetCalcPy-1.2.6.dist-info/LICENSE.txt
SetCalcPy-1.2.6.dist-info/METADATA
SetCalcPy-1.2.6.dist-info/WHEEL
SetCalcPy-1.2.6.dist-info/top_level.txt
SetCalcPy-1.2.6.dist-info/RECORD
