Metadata-Version: 2.1
Name: SetCalcPy
Version: 1.2.6
Summary: A library for performing basic set theory operations.
Home-page: https://github.com/SockRocks/Python-Elementary-Set-Theory-Calculator
Author: Ethan Gaver
Author-email: ethaneggcode@gmail.com
License: GNU
Keywords: calculator,homework-help,set-theory
Requires-Python: >=3.11.5
License-File: LICENSE.txt
Provides-Extra: dev
Requires-Dist: twine >=4.0.2 ; extra == 'dev'
